README.rst
pyproject.toml
setup.py
simple_aws_lambda_maker/__init__.py
simple_aws_lambda_maker/actions.py
simple_aws_lambda_maker/collector.py
simple_aws_lambda_maker/errors.py
simple_aws_lambda_maker/executor.py
simple_aws_lambda_maker/formatter.py
simple_aws_lambda_maker/maker.py
simple_aws_lambda_maker/options.py
simple_aws_lambda_maker.egg-info/PKG-INFO
simple_aws_lambda_maker.egg-info/SOURCES.txt
simple_aws_lambda_maker.egg-info/dependency_links.txt
simple_aws_lambda_maker.egg-info/entry_points.txt
simple_aws_lambda_maker.egg-info/requires.txt
simple_aws_lambda_maker.egg-info/top_level.txt