Metadata-Version: 1.2
Name: simple-aws-lambda-maker
Version: 0.3.0
Summary: Very simple deploy tool for aws lambda
Home-page: https://github.com/delfick/simple-aws-lambda-maker
Author: Stephen Moore
Author-email: github@delfick.com
License: MIT
Keywords: aws lambda
Platform: UNKNOWN
Requires-Python: >= 3.6
